github_app_user_auth/__init__.py
github_app_user_auth/auth.py
github_app_user_auth-1.1.dist-info/LICENSE
github_app_user_auth-1.1.dist-info/METADATA
github_app_user_auth-1.1.dist-info/WHEEL
github_app_user_auth-1.1.dist-info/entry_points.txt
github_app_user_auth-1.1.dist-info/top_level.txt
github_app_user_auth-1.1.dist-info/RECORD
