Metadata-Version: 2.1
Name: github-app-user-auth
Version: 1.1
Summary: Collection of git-credential helpers
Home-page: https://github.com/yuvipanda/github-app-user-auth
Author: Yuvi Panda
Author-email: yuvipanda@gmail.com
License: 3-clause BSD
Platform: any
License-File: LICENSE
Requires-Dist: requests
